status_page_demo_site/__init__.py
status_page_demo_site/forms.py
status_page_demo_site/urls.py
status_page_demo_site/views.py
status_page_demo_site/templates/demo_login.html
status_page_demo_site/tests/__init__.py
status_page_demo_site-0.1.2.dist-info/METADATA
status_page_demo_site-0.1.2.dist-info/WHEEL
status_page_demo_site-0.1.2.dist-info/top_level.txt
status_page_demo_site-0.1.2.dist-info/RECORD
