Metadata-Version: 2.1
Name: status-page-demo-site
Version: 0.1.2
Summary: HerrTxbias status_page_demo_site
Author-email: HerrTxbias <admin@herrtxbias.net>
License: MIT
Keywords: Status-Page,HerrTxbias,Plugin
Classifier: Programming Language :: Python :: 3
Requires-Python: >=3.8
